pwiki/__init__.py
pwiki/dwrap.py
pwiki/gquery.py
pwiki/mquery.py
pwiki/ns.py
pwiki/oquery.py
pwiki/query_constants.py
pwiki/query_utils.py
pwiki/utils.py
pwiki/waction.py
pwiki/wiki.py
pwiki/wparser.py
pwiki-1.3.1.dist-info/LICENSE.md
pwiki-1.3.1.dist-info/METADATA
pwiki-1.3.1.dist-info/WHEEL
pwiki-1.3.1.dist-info/top_level.txt
pwiki-1.3.1.dist-info/RECORD
