Metadata-Version: 2.1
Name: pwiki
Version: 1.3.1
Summary: A Python library for effortlessly interacting with Wikipedia/MediaWiki
Home-page: https://github.com/fastily/pwiki
Author: Fastily
Author-email: fastily@users.noreply.github.com
Project-URL: Bug Tracker, https://github.com/fastily/pwiki/issues
Classifier: Natural Language :: English
Classifier: Programming Language :: Python :: 3
Classifier: Programming Language :: Python :: 3.9
Classifier: License :: OSI Approved :: GNU General Public License v3 (GPLv3)
Classifier: Operating System :: OS Independent
Requires-Python: >=3.9
License-File: LICENSE.md
Requires-Dist: requests
